parsel_cli/__init__.py
parsel_cli/__main__.py
parsel_cli/cli.py
parsel_cli/utils.py
parsel_cli-0.2.0.dist-info/DESCRIPTION.rst
parsel_cli-0.2.0.dist-info/METADATA
parsel_cli-0.2.0.dist-info/RECORD
parsel_cli-0.2.0.dist-info/WHEEL
parsel_cli-0.2.0.dist-info/entry_points.txt
parsel_cli-0.2.0.dist-info/metadata.json
parsel_cli-0.2.0.dist-info/top_level.txt
