Metadata-Version: 2.0
Name: parsel-cli
Version: 0.2.0
Summary: Parsel Command Line Interface
Home-page: https://github.com/rolando/parsel-cli
Author: Rolando Espinoza
Author-email: rolando at rmax.io
License: MIT
Keywords: parsel-cli
Platform: UNKNOWN
Classifier: Development Status :: 2 - Pre-Alpha
Classifier: Intended Audience :: Developers
Classifier: License :: OSI Approved :: MIT License
Classifier: Natural Language :: English
Classifier: Programming Language :: Python :: 2
Classifier: Programming Language :: Python :: 2.7
Classifier: Programming Language :: Python :: 3
Classifier: Programming Language :: Python :: 3.4
Classifier: Programming Language :: Python :: 3.5
Requires-Dist: parsel
